morphik/__init__.py
morphik/_internal.py
morphik/_scoped_ops.py
morphik/async_.py
morphik/exceptions.py
morphik/models.py
morphik/rules.py
morphik/sync.py
morphik/tests/README.md
morphik/tests/__init__.py
morphik/tests/example_usage.py
morphik/tests/test_async.py
morphik/tests/test_scoped_ops_unit.py
morphik/tests/test_sync.py
morphik/tests/test_docs/sample1.txt
morphik/tests/test_docs/sample2.txt
morphik/tests/test_docs/sample3.txt
morphik-1.1.2.dist-info/METADATA
morphik-1.1.2.dist-info/WHEEL
morphik-1.1.2.dist-info/RECORD
